pwem/__init__.py
pwem/bibtex.py
pwem/constants.py
pwem/protocols.conf
pwem/scipion_icon.png
pwem/utils.py
pwem/cmd/chimera_client.py
pwem/cmd/convert.py
pwem/cmd/program.py
pwem/convert/__init__.py
pwem/convert/atom_struct.py
pwem/convert/headers.py
pwem/convert/pdb_list.py
pwem/convert/sequence.py
pwem/convert/symmetry.py
pwem/convert/transformations.py
pwem/convert/trigonometry.py
pwem/convert/utils.py
pwem/emlib/__init__.py
pwem/emlib/_libNone.py
pwem/emlib/lib.py
pwem/emlib/image/__init__.py
pwem/emlib/image/image_handler.py
pwem/emlib/image/image_readers.py
pwem/emlib/metadata/__init__.py
pwem/emlib/metadata/utils.py
pwem/objects/__init__.py
pwem/objects/data.py
pwem/objects/data_flexhub.py
pwem/objects/data_tiltpairs.py
pwem/protocols/__init__.py
pwem/protocols/parallel.py
pwem/protocols/protocol.py
pwem/protocols/protocol_2d.py
pwem/protocols/protocol_3d.py
pwem/protocols/protocol_align_movies.py
pwem/protocols/protocol_alignment_assign.py
pwem/protocols/protocol_alignment_invertHand.py
pwem/protocols/protocol_base_flexhub.py
pwem/protocols/protocol_batch.py
pwem/protocols/protocol_boxsize_checkpoint.py
pwem/protocols/protocol_boxsize_parameters.py
pwem/protocols/protocol_classes_selector.py
pwem/protocols/protocol_create_stream_data.py
pwem/protocols/protocol_ctf_assign.py
pwem/protocols/protocol_extract_coordinates.py
pwem/protocols/protocol_mathematical_operator.py
pwem/protocols/protocol_micrographs.py
pwem/protocols/protocol_movie_eraser.py
pwem/protocols/protocol_movies.py
pwem/protocols/protocol_origin_sampling_volume.py
pwem/protocols/protocol_particles.py
pwem/protocols/protocol_particles_picking.py
pwem/protocols/protocol_pdf_report.py
pwem/protocols/protocol_projection_edit.py
pwem/protocols/protocol_set_editor.py
pwem/protocols/protocol_set_filter.py
pwem/protocols/protocol_sets.py
pwem/protocols/protocol_tests.py
pwem/protocols/protocol_tiltpairs.py
pwem/protocols/protocol_tools.py
pwem/protocols/protocol_wait.py
scipion_em-3.10.2.dist-info/LICENSE
scipion_em-3.10.2.dist-info/METADATA
scipion_em-3.10.2.dist-info/WHEEL
scipion_em-3.10.2.dist-info/entry_points.txt
scipion_em-3.10.2.dist-info/top_level.txt
scipion_em-3.10.2.dist-info/RECORD
